wrfhydropy/__init__.py
wrfhydropy/core/__init__.py
wrfhydropy/core/collection.py
wrfhydropy/core/cycle.py
wrfhydropy/core/domain.py
wrfhydropy/core/ensemble.py
wrfhydropy/core/ensemble_tools.py
wrfhydropy/core/evaluation.py
wrfhydropy/core/ioutils.py
wrfhydropy/core/job.py
wrfhydropy/core/model.py
wrfhydropy/core/namelist.py
wrfhydropy/core/outputdiffs.py
wrfhydropy/core/schedulers.py
wrfhydropy/core/simulation.py
wrfhydropy/core/teams.py
wrfhydropy/tests/__init__.py
wrfhydropy/tests/conftest.py
wrfhydropy/tests/test_collection.py
wrfhydropy/tests/test_cycle.py
wrfhydropy/tests/test_domain.py
wrfhydropy/tests/test_ensemble.py
wrfhydropy/tests/test_evaluation.py
wrfhydropy/tests/test_ioutils.py
wrfhydropy/tests/test_job.py
wrfhydropy/tests/test_model.py
wrfhydropy/tests/test_namelist.py
wrfhydropy/tests/test_outputdiffs.py
wrfhydropy/tests/test_schedulers_pbs.py
wrfhydropy/tests/test_simulation.py
wrfhydropy/tests/test_utils.py
wrfhydropy/tests/data/__init__.py
wrfhydropy/tests/data/collection_data_download.py
wrfhydropy/tests/data/collection_data_recipe.py
wrfhydropy/tests/data/evaluation_answer_reprs.py
wrfhydropy/tests/data/gdrive_download.py
wrfhydropy/tests/data/nan_na_files_recipe.py
wrfhydropy/util/__init__.py
wrfhydropy/util/xrcmp.py
wrfhydropy/util/xrnan.py
wrfhydropy-0.0.21.dist-info/METADATA
wrfhydropy-0.0.21.dist-info/WHEEL
wrfhydropy-0.0.21.dist-info/top_level.txt
wrfhydropy-0.0.21.dist-info/RECORD
