Metadata-Version: 2.1
Name: wrfhydropy
Version: 0.0.21
Summary: API for the WRF-Hydro model
Home-page: https://github.com/NCAR/wrf_hydro_py
Author: WRF-Hydro Team
Author-email: soren@ucar.edu
License: MIT
Requires-Python: >=3.7
Requires-Dist: boltons >=23.1.1
Requires-Dist: bs4 >=0.0.1
Requires-Dist: dask[bag] >=2.14.0
Requires-Dist: deepdiff >=6.2.3
Requires-Dist: f90nml >=1.2
Requires-Dist: importlib-metadata ==4.13.0
Requires-Dist: netCDF4 >=1.5.3
Requires-Dist: numpy >=1.23.5
Requires-Dist: pandas >=1.3.5
Requires-Dist: properscoring ==0.1
Requires-Dist: pytest <=7.4.4
Requires-Dist: pytest-html >=3.0.0
Requires-Dist: pytest-datadir-ng >=1.1.1
Requires-Dist: pytest-lazy-fixture >=0.6.3
Requires-Dist: requests >=2.23.0
Requires-Dist: spotpy >=1.6.0
Requires-Dist: urllib3 >=2.0.2
Requires-Dist: xarray >=0.19
